customerio/analytics/__init__.py
customerio/analytics/client.py
customerio/analytics/consumer.py
customerio/analytics/request.py
customerio/analytics/utils.py
customerio/analytics/version.py
customerio_cdp_analytics-0.0.2.dist-info/LICENSE
customerio_cdp_analytics-0.0.2.dist-info/METADATA
customerio_cdp_analytics-0.0.2.dist-info/WHEEL
customerio_cdp_analytics-0.0.2.dist-info/top_level.txt
customerio_cdp_analytics-0.0.2.dist-info/RECORD
